{
  "generated_at": "2026-07-21T09:37:42+00:00",
  "dashboard_url": "https://LPT111.github.io/daily_stock_analysis/",
  "stock_report": "report_20260721.md",
  "market_report": "market_review_20260721.md",
  "validations": [
    {
      "code": "600118",
      "policy": "仅 status=confirmed 的字段可用于结论；待核实字段必须忽略。",
      "metrics": {
        "price": {
          "status": "confirmed",
          "value": 61.29,
          "display": "61.29",
          "interpretation": "腾讯财经与东方财富交叉核验一致。",
          "sources": {
            "腾讯财经": 61.29,
            "东方财富": 61.29
          }
        },
        "change_pct": {
          "status": "confirmed",
          "value": 3.04,
          "display": "3.04",
          "interpretation": "腾讯财经与东方财富交叉核验一致。",
          "sources": {
            "腾讯财经": 3.04,
            "东方财富": 3.04
          }
        },
        "dynamic_pe": {
          "status": "confirmed",
          "value": -424.42,
          "display": "-424.42（亏损状态）",
          "interpretation": "动态市盈率为负，表示当前口径下盈利为负，不能按正 PE 倍数进行估值判断。",
          "sources": {
            "腾讯财经": -424.42,
            "东方财富": -424.42
          }
        },
        "pb": {
          "status": "confirmed",
          "value": 11.47,
          "display": "11.47",
          "interpretation": "腾讯财经与东方财富交叉核验一致。",
          "sources": {
            "腾讯财经": 11.46,
            "东方财富": 11.48
          }
        }
      },
      "raw_sources": [
        {
          "source": "腾讯财经",
          "price": 61.29,
          "previous_close": 59.48,
          "change_pct": 3.04,
          "dynamic_pe": -424.42,
          "pb": 11.46,
          "source_url": "https://gu.qq.com/sh600118"
        },
        {
          "source": "东方财富",
          "price": 61.29,
          "previous_close": 59.48,
          "change_pct": 3.04,
          "dynamic_pe": -424.42,
          "pb": 11.48,
          "source_url": "https://quote.eastmoney.com/sh600118.html"
        }
      ],
      "errors": []
    }
  ],
  "sector_news": {
    "items": [
      {
        "title": "From Hampton to Mars: How NASA Langley Helped Land on the Red Planet",
        "published_at": "2026-07-20T15:47+00:00",
        "source": "NASA News",
        "url": "https://www.nasa.gov/general/from-hampton-to-mars-how-nasa-langley-helped-land-on-the-red-planet/",
        "category": "卫星与商业航天",
        "region": "国际",
        "source_weight": 14
      },
      {
        "title": "Our First View of the Surface of Mars",
        "published_at": "2026-07-20T15:38+00:00",
        "source": "NASA News",
        "url": "https://www.nasa.gov/image-article/our-first-view-of-the-surface-of-mars/",
        "category": "卫星与商业航天",
        "region": "国际",
        "source_weight": 14
      },
      {
        "title": "The Growing Crescent of Mars as NASA’s Psyche Mission Approaches",
        "published_at": "2026-07-17T22:32+00:00",
        "source": "NASA News",
        "url": "https://science.nasa.gov/photojournal/the-growing-crescent-of-mars-as-nasas-psyche-mission-approaches/",
        "category": "卫星与商业航天",
        "region": "国际",
        "source_weight": 14
      },
      {
        "title": "IHI explores Kuva hyperspectral satellites for Japan’s multi-sensor constellation",
        "published_at": "2026-07-21T07:00+00:00",
        "source": "SpaceNews",
        "url": "https://spacenews.com/ihi-explores-kuva-hyperspectral-satellites-for-japans-multi-sensor-constellation/",
        "category": "卫星与商业航天",
        "region": "国际",
        "source_weight": 13
      },
      {
        "title": "New executive order tightens defense supply chain waiver rules",
        "published_at": "2026-07-20T20:30+00:00",
        "source": "Defense News",
        "url": "https://www.defensenews.com/news/pentagon-congress/2026/07/20/new-executive-order-tightens-defense-supply-chain-waiver-rules/",
        "category": "军工与国防科技",
        "region": "国际",
        "source_weight": 13
      },
      {
        "title": "Doodle Labs eyes US, European production sites as demand soars for jam-resistant drones",
        "published_at": "2026-07-20T16:00+00:00",
        "source": "Defense News",
        "url": "https://www.defensenews.com/industry/2026/07/20/doodle-labs-eyes-us-european-production-sites-as-demand-soars-for-jam-resistant-drones/",
        "category": "军工与国防科技",
        "region": "国际",
        "source_weight": 13
      },
      {
        "title": "Lockheed Martin’s Morfius X-Rotor built to fry 50 enemy drones in one flight",
        "published_at": "2026-07-20T15:04+00:00",
        "source": "Defense News",
        "url": "https://www.defensenews.com/industry/techwatch/2026/07/20/lockheed-martins-morfius-x-rotor-built-to-fry-50-enemy-drones-in-one-flight/",
        "category": "军工与国防科技",
        "region": "国际",
        "source_weight": 13
      },
      {
        "title": "Lockheed Martin announces cheaper Patriot interceptor missile",
        "published_at": "2026-07-20T14:44+00:00",
        "source": "Defense News",
        "url": "https://www.defensenews.com/news/your-military/2026/07/20/lockheed-martin-announces-cheaper-patriot-interceptor-missile/",
        "category": "军工与国防科技",
        "region": "国际",
        "source_weight": 13
      },
      {
        "title": "AI rocket engine startup LegendSpace raises $29.5 million angel round",
        "published_at": "2026-07-20T11:18+00:00",
        "source": "SpaceNews",
        "url": "https://spacenews.com/ai-rocket-engine-startup-legendspace-raises-29-5-million-angel-round/",
        "category": "卫星与商业航天",
        "region": "国际",
        "source_weight": 13
      },
      {
        "title": "Pentagon awards $7.1 million to expand U.S. production of cover glass for satellites",
        "published_at": "2026-07-18T16:59+00:00",
        "source": "SpaceNews",
        "url": "https://spacenews.com/pentagon-awards-7-1-million-to-expand-u-s-production-of-cover-glass-for-satellites/",
        "category": "卫星与商业航天",
        "region": "国际",
        "source_weight": 13
      },
      {
        "title": "Bluestaq Launches BLUESTAQ / ARQ Defense-Grade Data Infrastructure Now Available for Commercial, Government, and Enterprise Organizations",
        "published_at": "2026-07-16T12:00+00:00",
        "source": "SpaceNews",
        "url": "https://spacenews.com/bluestaq-launches-bluestaq-arq-defense-grade-data-infrastructure-now-available-for-commercial-government-and-enterprise-organizations/",
        "category": "军工与国防科技",
        "region": "国际",
        "source_weight": 13
      },
      {
        "title": "China’s AI models have Trump’s AI world at war with itself",
        "published_at": "2026-07-20T18:00+00:00",
        "source": "MIT Technology Review",
        "url": "https://www.technologyreview.com/2026/07/20/1140675/chinas-ai-models-have-trumps-ai-world-at-war-with-itself/",
        "category": "科技与芯片",
        "region": "国际",
        "source_weight": 12
      },
      {
        "title": "The Download: AI hiring biases, and weather data sabotage",
        "published_at": "2026-07-20T12:10+00:00",
        "source": "MIT Technology Review",
        "url": "https://www.technologyreview.com/2026/07/20/1140664/the-download-ai-hiring-biases-weather-data-sabotage/",
        "category": "科技与芯片",
        "region": "国际",
        "source_weight": 12
      },
      {
        "title": "AI is more likely than humans to form biases when hiring",
        "published_at": "2026-07-20T08:39+00:00",
        "source": "MIT Technology Review",
        "url": "https://www.technologyreview.com/2026/07/20/1140655/ai-biases-hiring-humans/",
        "category": "科技与芯片",
        "region": "国际",
        "source_weight": 12
      },
      {
        "title": "The Download: perimenopause misinformation and China’s latest AI leap",
        "published_at": "2026-07-17T12:10+00:00",
        "source": "MIT Technology Review",
        "url": "https://www.technologyreview.com/2026/07/17/1140640/the-download-perimenopause-misinformation-china-moonshot-ai/",
        "category": "科技与芯片",
        "region": "国际",
        "source_weight": 12
      },
      {
        "title": "AI ‘ghosts’ can comfort mourners — even when the bots get the facts wrong",
        "published_at": "2026-07-20T15:00+00:00",
        "source": "Science News",
        "url": "https://www.sciencenews.org/article/ai-ghosts-grief-facts-wrong-chatbot",
        "category": "科技与芯片",
        "region": "国际",
        "source_weight": 11
      },
      {
        "title": "AI is not ready to fly solo in space",
        "published_at": "2026-07-15T14:00+00:00",
        "source": "Science News",
        "url": "https://www.sciencenews.org/article/ai-task-completion-ability-space-scifi",
        "category": "科技与芯片",
        "region": "国际",
        "source_weight": 11
      },
      {
        "title": "Firefighting drones in the works as wildfires plague US nearly year-round",
        "published_at": "2026-07-20T21:55+00:00",
        "source": "Ars Technica",
        "url": "https://arstechnica.com/ai/2026/07/firefighting-drones-in-the-works-as-wildfires-plague-us-nearly-year-round/",
        "category": "军工与国防科技",
        "region": "国际",
        "source_weight": 9
      },
      {
        "title": "Amazon's Zoox issues software recall after robotaxi drove into heavy smoke",
        "published_at": "2026-07-17T14:42+00:00",
        "source": "CNBC Technology",
        "url": "https://www.cnbc.com/2026/07/17/amazon-zoox-recalls-robotaxi-smoke.html",
        "category": "机器人与具身智能",
        "region": "国际",
        "source_weight": 9
      },
      {
        "title": "BrainCo demos thought-controlled robots at WAIC 2026",
        "published_at": "2026-07-21T07:59+00:00",
        "source": "TechNode",
        "url": "https://technode.com/2026/07/21/brainco-demos-thought-controlled-robots-at-waic-2026/",
        "category": "机器人与具身智能",
        "region": "国际",
        "source_weight": 8
      },
      {
        "title": "XPENG releases TuringViT for smart driving and humanoid robots",
        "published_at": "2026-07-21T07:53+00:00",
        "source": "TechNode",
        "url": "https://technode.com/2026/07/21/xpeng-releases-turingvit-for-smart-driving-and-humanoid-robots/",
        "category": "机器人与具身智能",
        "region": "国际",
        "source_weight": 8
      },
      {
        "title": "全球首款机器人手机：荣耀 Robot Phone 首日预约量超荣耀历代旗舰产品",
        "published_at": "2026-07-21T07:07+00:00",
        "source": "IT之家",
        "url": "https://www.ithome.com/0/979/555.htm",
        "category": "机器人与具身智能",
        "region": "国内",
        "source_weight": 8
      },
      {
        "title": "Elon Musk says robot fights are fun after watching China’s humanoid robot battle",
        "published_at": "2026-07-20T08:34+00:00",
        "source": "TechNode",
        "url": "https://technode.com/2026/07/20/elon-musk-says-robot-fights-are-fun-after-watching-chinas-humanoid-robot-battle/",
        "category": "机器人与具身智能",
        "region": "国际",
        "source_weight": 8
      },
      {
        "title": "Yimu Tech raises over RMB1 billion for robot tactile sensing and production",
        "published_at": "2026-07-20T08:09+00:00",
        "source": "TechNode",
        "url": "https://technode.com/2026/07/20/yimu-tech-raises-over-rmb1-billion-for-robot-tactile-sensing-and-production/",
        "category": "机器人与具身智能",
        "region": "国际",
        "source_weight": 8
      }
    ],
    "errors": [
      "国内科技新闻: 429 Client Error: Too Many Requests for url: https://api.gdeltproject.org/api/v2/doc/doc?query=%28%E5%8D%AB%E6%98%9F+OR+%E8%88%AA%E5%A4%A9+OR+%E5%8C%97%E6%96%97+OR+%E6%9C%BA%E5%99%A8%E4%BA%BA+OR+%E5%85%B7%E8%BA%AB%E6%99%BA%E8%83%BD+OR+%E8%8A%AF%E7%89%87+OR+%E5%8D%8A%E5%AF%BC%E4%BD%93+OR+%E4%BA%BA%E5%B7%A5%E6%99%BA%E8%83%BD+OR+%E5%86%9B%E5%B7%A5+OR+%E5%9B%BD%E9%98%B2%E7%A7%91%E6%8A%80%29+sourcelang%3AChinese&mode=artlist&format=json&maxrecords=24&sort=datedesc&timespan=3d",
      "国际科技新闻: 429 Client Error: Too Many Requests for url: https://api.gdeltproject.org/api/v2/doc/doc?query=%28satellite+OR+spaceflight+OR+robotics+OR+humanoid+OR+semiconductor+OR+%22artificial+intelligence%22+OR+%22defense+technology%22%29+sourcelang%3AEnglish&mode=artlist&format=json&maxrecords=24&sort=datedesc&timespan=3d"
    ],
    "policy": "仅展示含标题、发布时间、来源和原文链接的新闻；不据此自动推断股价因果。"
  },
  "digest": "【A股科技主题决策雷达】\n个股建议：减仓（基于近3个月K线，保守模式）\n执行参考：买入区间 暂不设置（空头排列，严禁追买）｜仓位 0成（空仓）或减仓至1成以内（持仓者）\n风控纪律：止损 持仓者：若跌破今日低点54.71元建议严格止损｜失效条件 未来3个交易日重新站稳3.04且量价修复，则减仓判断失效并重新评估\n大盘摘要：🎯 大盘复盘 2026-07-21 大盘复盘 今日市场呈现极致结构分化，科创50与创业板指放量暴涨，上证相对滞涨，板块热度高度集中于科技与高端制造；日内涨停家数虽多但跌停同步存在，情绪局部亢奋但宽度不足。明日核心矛盾在于科技主线能否持续扩散，以及权重板块是否出现补涨或拖累。 一、盘面总览 主要指数全线收红，但内部剧烈分化：科创50暴涨10.73%，创业板指大…\n600118 双源校验：价格：61.29；涨跌幅：3.04；动态PE：-424.42（亏损状态）；PB：11.47\n\n可核验科技新闻：\n- 卫星与商业航天：From Hampton to Mars: How NASA Langley Helped Land on the Red Planet（NASA News，2026-07-20T15:47+00:00）\n  https://www.nasa.gov/general/from-hampton-to-mars-how-nasa-langley-helped-land-on-the-red-planet/\n- 军工与国防科技：New executive order tightens defense supply chain waiver rules（Defense News，2026-07-20T20:30+00:00）\n  https://www.defensenews.com/news/pentagon-congress/2026/07/20/new-executive-order-tightens-defense-supply-chain-waiver-rules/\n- 科技与芯片：China’s AI models have Trump’s AI world at war with itself（MIT Technology Review，2026-07-20T18:00+00:00）\n  https://www.technologyreview.com/2026/07/20/1140675/chinas-ai-models-have-trumps-ai-world-at-war-with-itself/\n- 机器人与具身智能：Amazon's Zoox issues software recall after robotaxi drove into heavy smoke（CNBC Technology，2026-07-17T14:42+00:00）\n  https://www.cnbc.com/2026/07/17/amazon-zoox-recalls-robotaxi-smoke.html\n\n网页版完整报告：https://LPT111.github.io/daily_stock_analysis/\n仅供研究参考，不构成投资建议。"
}